py2hackCraft/__init__.py
py2hackCraft/material.py
py2hackCraft/modules.py
py2hackcraft2-1.1.45.dist-info/METADATA
py2hackcraft2-1.1.45.dist-info/WHEEL
py2hackcraft2-1.1.45.dist-info/top_level.txt
py2hackcraft2-1.1.45.dist-info/RECORD
